<?xml version="1.0" encoding="UTF-8"?>
<objects serializationModel="Studio.02.01.00">
	<object class="EncodingSetting" id="{40087a4a-a244-478b-8ef7-3a8a942d1ab7}">
		<property name="encodingFormat">
			<value>3</value>
		</property>
		<property name="quality">
			<value>37</value>
		</property>
		<relationship name="platform">
			<destination>{aa9c1156-ef17-4341-870c-f5819669d113}</destination>
		</relationship>
		<relationship name="encodable">
			<destination>{b3e184ae-c63d-4c3b-a8bf-6a09fc3c7496}</destination>
		</relationship>
	</object>
</objects>
